azucar_reactive_websocket/__init__.py
azucar_reactive_websocket/imagen_handler.py
azucar_reactive_websocket/reactive_websocket_handler.py
azucar_reactive_websocket-0.2.1.dist-info/METADATA
azucar_reactive_websocket-0.2.1.dist-info/WHEEL
azucar_reactive_websocket-0.2.1.dist-info/top_level.txt
azucar_reactive_websocket-0.2.1.dist-info/RECORD
